superannotate/__init__.py
superannotate/lib/__init__.py
superannotate/lib/app/__init__.py
superannotate/lib/app/common.py
superannotate/lib/app/exceptions.py
superannotate/lib/app/helpers.py
superannotate/lib/app/serializers.py
superannotate/lib/app/analytics/__init__.py
superannotate/lib/app/analytics/aggregators.py
superannotate/lib/app/analytics/common.py
superannotate/lib/app/bin/__init__.py
superannotate/lib/app/bin/superannotate.py
superannotate/lib/app/input_converters/__init__.py
superannotate/lib/app/input_converters/conversion.py
superannotate/lib/app/input_converters/export_from_sa_conversions.py
superannotate/lib/app/input_converters/import_to_sa_conversions.py
superannotate/lib/app/input_converters/sa_conversion.py
superannotate/lib/app/input_converters/converters/__init__.py
superannotate/lib/app/input_converters/converters/baseStrategy.py
superannotate/lib/app/input_converters/converters/converters.py
superannotate/lib/app/input_converters/converters/sa_json_helper.py
superannotate/lib/app/input_converters/converters/coco_converters/__init__.py
superannotate/lib/app/input_converters/converters/coco_converters/coco_api.py
superannotate/lib/app/input_converters/converters/coco_converters/coco_converter.py
superannotate/lib/app/input_converters/converters/coco_converters/coco_strategies.py
superannotate/lib/app/input_converters/converters/coco_converters/coco_to_sa_pixel.py
superannotate/lib/app/input_converters/converters/coco_converters/coco_to_sa_vector.py
superannotate/lib/app/input_converters/converters/coco_converters/sa_pixel_to_coco.py
superannotate/lib/app/input_converters/converters/coco_converters/sa_vector_to_coco.py
superannotate/lib/app/input_converters/converters/dataloop_converters/__init__.py
superannotate/lib/app/input_converters/converters/dataloop_converters/dataloop_helper.py
superannotate/lib/app/input_converters/converters/dataloop_converters/dataloop_strategies.py
superannotate-4.5.0.dist-info/LICENSE
superannotate-4.5.0.dist-info/METADATA
superannotate-4.5.0.dist-info/WHEEL
superannotate-4.5.0.dist-info/entry_points.txt
superannotate-4.5.0.dist-info/top_level.txt
superannotate-4.5.0.dist-info/RECORD
