Metadata-Version: 2.1
Name: superannotate
Version: 4.5.0
Summary: Python SDK to SuperAnnotate platform
Home-page: https://github.com/superannotateai/superannotate-python-sdk
Author: SuperAnnotate AI
Author-email: support@superannotate.com
License: MIT
Project-URL: Documentation, https://superannotate.readthedocs.io/en/stable/
Classifier: Programming Language :: Python
Classifier: Programming Language :: Python :: 3
Classifier: Programming Language :: Python :: 3.7
Classifier: Programming Language :: Python :: 3.8
Classifier: Programming Language :: Python :: 3.9
Classifier: Programming Language :: Python :: 3.10
Classifier: Programming Language :: Python :: 3.11
Requires-Python: >=3.7
License-File: LICENSE
Requires-Dist: pydantic!=2.0.*,<3,>=1.10
Requires-Dist: aiohttp~=3.8
Requires-Dist: boto3~=1.26
Requires-Dist: opencv-python-headless~=4.7
Requires-Dist: plotly~=5.14
Requires-Dist: pandas~=2.0
Requires-Dist: pillow>=9.5,~=10.0
Requires-Dist: tqdm~=4.66
Requires-Dist: requests==2.*
Requires-Dist: aiofiles==23.*
Requires-Dist: fire==0.4.0
Requires-Dist: mixpanel==4.8.3
Requires-Dist: superannotate-schemas==1.0.49
